taew/__init__.py
taew/ew.py
taew/taew.py
taew-0.0.2.dist-info/LICENSE
taew-0.0.2.dist-info/METADATA
taew-0.0.2.dist-info/WHEEL
taew-0.0.2.dist-info/top_level.txt
taew-0.0.2.dist-info/RECORD
