Metadata-Version: 2.1
Name: taew
Version: 0.0.2
Summary: UNKNOWN
Home-page: UNKNOWN
Author: Edward Wong
Author-email: eternal.edward1997@gmail.com
License: UNKNOWN
Platform: UNKNOWN
Requires-Python: >= 3.7
